README.md
setup.py
pyboto3/__init__.py
pyboto3/accessanalyzer.py
pyboto3/acm.py
pyboto3/acmpca.py
pyboto3/alexaforbusiness.py
pyboto3/amplify.py
pyboto3/apigateway.py
pyboto3/apigatewaymanagementapi.py
pyboto3/apigatewayv2.py
pyboto3/appconfig.py
pyboto3/applicationautoscaling.py
pyboto3/applicationdiscoveryservice.py
pyboto3/applicationinsights.py
pyboto3/appmesh.py
pyboto3/appstream.py
pyboto3/appsync.py
pyboto3/athena.py
pyboto3/augmentedairuntime.py
pyboto3/autoscaling.py
pyboto3/autoscalingplans.py
pyboto3/backup.py
pyboto3/batch.py
pyboto3/boto3_interface_generator.py
pyboto3/budgets.py
pyboto3/chime.py
pyboto3/clients.py
pyboto3/cloud9.py
pyboto3/clouddirectory.py
pyboto3/cloudformation.py
pyboto3/cloudfront.py
pyboto3/cloudhsm.py
pyboto3/cloudhsmv2.py
pyboto3/cloudsearch.py
pyboto3/cloudsearchdomain.py
pyboto3/cloudtrail.py
pyboto3/cloudwatch.py
pyboto3/cloudwatchevents.py
pyboto3/cloudwatchlogs.py
pyboto3/codebuild.py
pyboto3/codecommit.py
pyboto3/codedeploy.py
pyboto3/codeguruprofiler.py
pyboto3/codegurureviewer.py
pyboto3/codepipeline.py
pyboto3/codestar.py
pyboto3/codestarconnections.py
pyboto3/codestarnotifications.py
pyboto3/cognitoidentity.py
pyboto3/cognitoidentityprovider.py
pyboto3/cognitosync.py
pyboto3/comprehend.py
pyboto3/comprehendmedical.py
pyboto3/computeoptimizer.py
pyboto3/configservice.py
pyboto3/connect.py
pyboto3/connectparticipant.py
pyboto3/costandusagereportservice.py
pyboto3/costexplorer.py
pyboto3/databasemigrationservice.py
pyboto3/dataexchange.py
pyboto3/datapipeline.py
pyboto3/datasync.py
pyboto3/dax.py
pyboto3/detective.py
pyboto3/devicefarm.py
pyboto3/directconnect.py
pyboto3/directoryservice.py
pyboto3/dlm.py
pyboto3/docdb.py
pyboto3/dynamodb.py
pyboto3/dynamodbstreams.py
pyboto3/ebs.py
pyboto3/ec2.py
pyboto3/ec2instanceconnect.py
pyboto3/ecr.py
pyboto3/ecs.py
pyboto3/efs.py
pyboto3/eks.py
pyboto3/elasticache.py
pyboto3/elasticbeanstalk.py
pyboto3/elasticinference.py
pyboto3/elasticloadbalancing.py
pyboto3.egg-info/PKG-INFO
pyboto3.egg-info/SOURCES.txt
pyboto3.egg-info/dependency_links.txt
pyboto3.egg-info/top_level.txt
pyboto3.egg-info/zip-safe